uquery/__init__.py
uquery/_version.py
uquery/configuration.py
uquery/dialect.py
uquery/engine.py
uquery/funcs.py
uquery/util.py
uquery/backends/doris/__init__.py
uquery/backends/doris/compiler_sa.py
uquery/backends/doris/datatype.py
uquery/backends/doris/doris_backend.py
uquery/backends/doris/registry.py
uquery/backends/doris/stream_loader.py
uquery/backends/doris/compiler/__init__.py
uquery/backends/doris/compiler/core.py
uquery/backends/doris/compiler/values.py
uquery-0.1.1.dist-info/LICENSE
uquery-0.1.1.dist-info/METADATA
uquery-0.1.1.dist-info/WHEEL
uquery-0.1.1.dist-info/top_level.txt
uquery-0.1.1.dist-info/RECORD
