Metadata-Version: 2.2
Name: uquery
Version: 0.1.1
Summary: Abstract away the complexity of multi-data source access with a unified interface
Author-email: wukong_tech <lianghua@wukongtz.com>
Classifier: Development Status :: 2 - Pre-Alpha
Classifier: Programming Language :: Python :: 3
Requires-Python: >=3.9
License-File: LICENSE
Requires-Dist: requests
Requires-Dist: oracledb
Requires-Dist: psycopg2-binary
Requires-Dist: sqlalchemy
Requires-Dist: pandas<2.2.0
Requires-Dist: pydash
Requires-Dist: cx_Oracle
Requires-Dist: toml
Requires-Dist: tqdm
Requires-Dist: sqlparse
Requires-Dist: ibis-framework[mysql]==7.1.0
Requires-Dist: sqlalchemy-doris[pymysql]==0.2.2
Requires-Dist: adbc_driver_manager
Requires-Dist: adbc_driver_flightsql
